.gitignore
CHANGELOG.md
LICENSE.md
MANIFEST.in
README.md
setup.cfg
setup.py
dac_picker/__init__.py
dac_picker/combo_picker.py
dac_picker/database.py
dac_picker/items_picker.py
dac_picker/pieces_picker.py
dac_picker/version.py
dac_picker.egg-info/PKG-INFO
dac_picker.egg-info/SOURCES.txt
dac_picker.egg-info/dependency_links.txt
dac_picker.egg-info/entry_points.txt
dac_picker.egg-info/requires.txt
dac_picker.egg-info/top_level.txt
dac_picker/database/ods2csv.sh
dac_picker/database/csv/classes.csv
dac_picker/database/csv/combos.csv
dac_picker/database/csv/items.csv
dac_picker/database/csv/pieces.csv
dac_picker/database/csv/species.csv
dac_picker/database/docs/Combos.ods
dac_picker/database/docs/Database.ods
dac_picker/database/temp/Combos.txt.0
dac_picker/database/temp/Database.txt.0
dac_picker/database/temp/Database.txt.1
dac_picker/database/temp/Database.txt.2
dac_picker/database/temp/Database.txt.3
dac_picker/images/items/Assault Cuirass.png
dac_picker/images/items/Attack Blade.png
dac_picker/images/items/Battle Fury.png
dac_picker/images/items/Black King Bar.png
dac_picker/images/items/Blade Mail.png
dac_picker/images/items/Blight Stone.png
dac_picker/images/items/Blink Dagger.png
dac_picker/images/items/Broad Sword.png
dac_picker/images/items/Chain Mail.png
dac_picker/images/items/Cloak.png
dac_picker/images/items/Crown.png
dac_picker/images/items/Crystalys.png
dac_picker/images/items/Daedalus.png
dac_picker/images/items/Dagon 1.png
dac_picker/images/items/Dagon 2.png
dac_picker/images/items/Dagon 3.png
dac_picker/images/items/Dagon 4.png
dac_picker/images/items/Dagon 5.png
dac_picker/images/items/Demon Edge.png
dac_picker/images/items/Desolator.png
dac_picker/images/items/Divine Rapier.png
dac_picker/images/items/Health Ring.png
dac_picker/images/items/Hood of Defiance.png
dac_picker/images/items/Hyperstone.png
dac_picker/images/items/Javelin.png
dac_picker/images/items/Kaya.png
dac_picker/images/items/Madness Mask.png
dac_picker/images/items/Maelstrom.png
dac_picker/images/items/Magi Robe.png
dac_picker/images/items/Mithril Hammer.png
dac_picker/images/items/Mjollnir.png
dac_picker/images/items/Monkey King Bar.png
dac_picker/images/items/Moon Shard.png
